setup.py
transloadit/__init__.py
transloadit/client.py
transloadit.egg-info/PKG-INFO
transloadit.egg-info/SOURCES.txt
transloadit.egg-info/dependency_links.txt
transloadit.egg-info/requires.txt
transloadit.egg-info/top_level.txt
transloadit.egg-info/zip-safe