Metadata-Version: 1.0
Name: transloadit
Version: 1.0.1
Summary: Library for interfacing with Transloadit's API
Home-page: http://github.com/joestump/python-transloadit
Author: Joe Stump
Author-email: joe@joestump.net
License: MIT License
Keywords: transloadit
Platform: UNKNOWN
